{
  "potentially_hazardous_neos": [
    {
      "name": "(2017 QY34)",
      "neo_reference_id": "3781301",
      "absolute_magnitude_h": 20.93,
      "estimated_diameter_m_min": 173.2028271414,
      "estimated_diameter_m_max": 387.2932953833,
      "close_approach": {
        "date_full": "2025-Sep-07 05:21",
        "orbiting_body": "Earth",
        "miss_distance_km": 61579875.35274692,
        "relative_velocity_km_s": 27.5457116905
      }
    }
  ],
  "date_utc": "2025-09-07",
  "snapshot_utc": "2025-09-07T12:15:41Z",
  "count": 1
}